Inxio/__init__.py
Inxio/file_type.py
Inxio/global_var.py
Inxio/android/__init__.py
Inxio/android/APP/__init__.py
Inxio/android/APP/app.py
Inxio/android/APP/permission.py
Inxio/android/core_components/Activity.py
Inxio/android/core_components/Bundle.py
Inxio/android/core_components/EventProcess.py
Inxio/android/core_components/Fragment.py
Inxio/android/core_components/Intent.py
Inxio/android/core_components/LocationManager.py
Inxio/android/core_components/NotificationManager.py
Inxio/android/core_components/PendingIntent.py
Inxio/android/core_components/SensorManager.py
Inxio/android/core_components/Service.py
Inxio/android/core_components/View.py
Inxio/android/core_components/View_Listeners.py
Inxio/android/core_components/XMLGenerator.py
Inxio/android/core_components/__init__.py
Inxio/android/executable/ExecutionBlock.py
Inxio/android/executable/__init__.py
Inxio/android/ui/__init__.py
Inxio/android/ui/Element/AlertDialog.py
Inxio/android/ui/Element/Text.py
Inxio/android/ui/Element/Toast.py
Inxio/android/ui/Element/__init__.py
Inxio/android/ui/Layout/FrameLayout.py
Inxio/android/ui/Layout/GridLayout.py
Inxio/android/ui/Layout/LayoutParams.py
Inxio/android/ui/Layout/LinearLayout.py
Inxio/android/ui/Layout/RelativeLayout.py
Inxio/android/ui/Layout/TableLayout.py
Inxio/android/ui/Layout/__init__.py
Inxio/android/vsp/VSPparser.py
Inxio/android/vsp/__init__.py
Inxio/android/vsp/try.py
Inxio/android/vsp/ty.py
Inxio/android/vsp/vsp2xml.py
Inxio/extends/__init__.py
Inxio/ui_shell/Button.py
Inxio/ui_shell/__init__.py
inxio-1.0.1.dist-info/METADATA
inxio-1.0.1.dist-info/WHEEL
inxio-1.0.1.dist-info/top_level.txt
inxio-1.0.1.dist-info/RECORD
