Metadata-Version: 2.1
Name: inxio
Version: 1.0.1
Summary: Inxio is a Python library for rapid development of Android applications. This is the first beta release
Home-page: UNKNOWN
Author: cemeye
Author-email: caomingyang2022@163.com
License: MIT
Platform: UNKNOWN
Classifier: Development Status :: 1 - Planning
Classifier: Intended Audience :: Developers
Classifier: Programming Language :: Python :: 3
Classifier: Operating System :: Unix
Classifier: Operating System :: MacOS :: MacOS X
Classifier: Operating System :: Microsoft :: Windows
